pydantic_changedetect/__init__.py
pydantic_changedetect/_compat.py
pydantic_changedetect/changedetect.py
pydantic_changedetect/py.typed
pydantic_changedetect/utils.py
pydantic_changedetect-0.10.1.dist-info/licenses/LICENSE
pydantic_changedetect-0.10.1.dist-info/WHEEL
pydantic_changedetect-0.10.1.dist-info/METADATA
pydantic_changedetect-0.10.1.dist-info/RECORD
